sphinxcontrib/toctree_plus/__init__.py
sphinxcontrib/toctree_plus/py.typed
toctree_plus-0.8.0.dist-info/LICENSE
toctree_plus-0.8.0.dist-info/METADATA
toctree_plus-0.8.0.dist-info/WHEEL
toctree_plus-0.8.0.dist-info/entry_points.txt
toctree_plus-0.8.0.dist-info/RECORD
