Metadata-Version: 2.2
Name: toctree-plus
Version: 0.8.0
Summary: Enhanced Sphinx TocTree which shows classes, functions etc. as if they were sections.
Author-email: Dominic Davis-Foster <dominic@davis-foster.co.uk>
License: BSD-3-Clause
Keywords: documentation,sphinx,sphinx-extension
Home-page: https://github.com/sphinx-toolbox/toctree_plus
Project-URL: Issue Tracker, https://github.com/sphinx-toolbox/toctree_plus/issues
Project-URL: Source Code, https://github.com/sphinx-toolbox/toctree_plus
Project-URL: Documentation, https://toctree-plus.readthedocs.io/en/latest
Platform: Windows
Platform: macOS
Platform: Linux
Classifier: Development Status :: 4 - Beta
Classifier: Framework :: Sphinx :: Extension
Classifier: Intended Audience :: Developers
Classifier: License :: OSI Approved :: BSD License
Classifier: Operating System :: OS Independent
Classifier: Programming Language :: Python
Classifier: Programming Language :: Python :: 3 :: Only
Classifier: Programming Language :: Python :: 3.6
Classifier: Programming Language :: Python :: 3.7
Classifier: Programming Language :: Python :: 3.8
Classifier: Programming Language :: Python :: 3.9
Classifier: Programming Language :: Python :: 3.10
Classifier: Programming Language :: Python :: 3.11
Classifier: Programming Language :: Python :: 3.12
Classifier: Programming Language :: Python :: Implementation :: CPython
Classifier: Programming Language :: Python :: Implementation :: PyPy
Classifier: Topic :: Documentation
Classifier: Topic :: Documentation :: Sphinx
Classifier: Topic :: Software Development :: Documentation
Classifier: Typing :: Typed
Requires-Python: >=3.6
Requires-Dist: docutils>=0.16
Requires-Dist: sphinx<7,>=3.0.3
Requires-Dist: sphinx-jinja2-compat>=0.2.0
